simple_chat/__init__.py
simple_chat/__main__.py
schat-0.1.0.dist-info/LICENSE
schat-0.1.0.dist-info/METADATA
schat-0.1.0.dist-info/WHEEL
schat-0.1.0.dist-info/entry_points.txt
schat-0.1.0.dist-info/RECORD
