Metadata-Version: 2.1
Name: schat
Version: 0.1.0
Summary: Chat with OpenAI ChatGPT in your command line, just for simple and ez
Home-page: https://github.com/HFrost0
License: MIT
Keywords: ChatGPT,CLI
Author: HFrost0
Author-email: hhlfrost@gmail.com
Requires-Python: >=3.10,<4
Classifier: License :: OSI Approved :: MIT License
Classifier: Operating System :: MacOS
Classifier: Operating System :: Microsoft :: Windows
Classifier: Programming Language :: Python :: 3
Classifier: Programming Language :: Python :: 3.10
Classifier: Programming Language :: Python :: 3.11
Classifier: Programming Language :: Python :: 3.10
Classifier: Programming Language :: Python :: 3.11
Classifier: Topic :: Utilities
Requires-Dist: openai
Requires-Dist: rich
Project-URL: Repository, https://github.com/HFrost0/Simple-Chat
